odoo/addons/mgmtsystem_review/README.rst
odoo/addons/mgmtsystem_review/__init__.py
odoo/addons/mgmtsystem_review/__manifest__.py
odoo/addons/mgmtsystem_review/data/ir_sequence.xml
odoo/addons/mgmtsystem_review/i18n/am.po
odoo/addons/mgmtsystem_review/i18n/ca.po
odoo/addons/mgmtsystem_review/i18n/de.po
odoo/addons/mgmtsystem_review/i18n/el_GR.po
odoo/addons/mgmtsystem_review/i18n/es.po
odoo/addons/mgmtsystem_review/i18n/es_CO.po
odoo/addons/mgmtsystem_review/i18n/es_ES.po
odoo/addons/mgmtsystem_review/i18n/fi.po
odoo/addons/mgmtsystem_review/i18n/fr.po
odoo/addons/mgmtsystem_review/i18n/gl.po
odoo/addons/mgmtsystem_review/i18n/hr_HR.po
odoo/addons/mgmtsystem_review/i18n/hu.po
odoo/addons/mgmtsystem_review/i18n/it.po
odoo/addons/mgmtsystem_review/i18n/lv.po
odoo/addons/mgmtsystem_review/i18n/mgmtsystem_review.pot
odoo/addons/mgmtsystem_review/i18n/nb.po
odoo/addons/mgmtsystem_review/i18n/nl.po
odoo/addons/mgmtsystem_review/i18n/nl_NL.po
odoo/addons/mgmtsystem_review/i18n/nn.po
odoo/addons/mgmtsystem_review/i18n/pt.po
odoo/addons/mgmtsystem_review/i18n/pt_BR.po
odoo/addons/mgmtsystem_review/i18n/pt_PT.po
odoo/addons/mgmtsystem_review/i18n/sl.po
odoo/addons/mgmtsystem_review/i18n/sv.po
odoo/addons/mgmtsystem_review/i18n/th.po
odoo/addons/mgmtsystem_review/i18n/tr.po
odoo/addons/mgmtsystem_review/i18n/vi.po
odoo/addons/mgmtsystem_review/migrations/13.0.1.0.0/noupdate_changes.xml
odoo/addons/mgmtsystem_review/migrations/13.0.1.0.0/post-migration.py
odoo/addons/mgmtsystem_review/models/__init__.py
odoo/addons/mgmtsystem_review/models/mgmtsystem_review.py
odoo/addons/mgmtsystem_review/models/mgmtsystem_review_line.py
odoo/addons/mgmtsystem_review/readme/CONTRIBUTORS.rst
odoo/addons/mgmtsystem_review/readme/DESCRIPTION.rst
odoo/addons/mgmtsystem_review/readme/USAGE.rst
odoo/addons/mgmtsystem_review/report/report.xml
odoo/addons/mgmtsystem_review/report/review.xml
odoo/addons/mgmtsystem_review/security/ir.model.access.csv
odoo13_addon_mgmtsystem_review-13.0.1.2.1.dist-info/METADATA
odoo13_addon_mgmtsystem_review-13.0.1.2.1.dist-info/WHEEL
odoo13_addon_mgmtsystem_review-13.0.1.2.1.dist-info/top_level.txt
odoo13_addon_mgmtsystem_review-13.0.1.2.1.dist-info/RECORD
